LICENSE
README.md
setup.py
usda_dashboard/__init__.py
usda_dashboard/_dash_USDA_dataIndex.py
usda_dashboard/_dash_USDA_dataIndex_run.py
usda_dashboard/_dash_fossil_CO2_emissions_2022.py
usda_dashboard/_dash_fossil_CO2_emissions_2022_run.py
usda_dashboard/_gadgets.py
usda_dashboard.egg-info/PKG-INFO
usda_dashboard.egg-info/SOURCES.txt
usda_dashboard.egg-info/dependency_links.txt
usda_dashboard.egg-info/top_level.txt
usda_dashboard/data/EDGARv7.0_FT2021_fossil_CO2_booklet_2022.xlsx
usda_dashboard/data/USDA_dataIndex.accdb
usda_dashboard/data/USDA_dataIndex_Backup.accdb
usda_dashboard/data/__init__.py
usda_dashboard/data/countries.geojson