Metadata-Version: 2.1
Name: usda-dashboard
Version: 0.0.1
Summary: dashborad for USDA
Home-page: https://github.com/richieBao
Author: richie bao
Author-email: richiebao@outlook.com
License: GNU
License-File: LICENSE
